strcs/__init__.py
strcs/annotations.py
strcs/args_extractor.py
strcs/decorator.py
strcs/errors.py
strcs/hints.py
strcs/hooks.py
strcs/memoized_property.py
strcs/meta.py
strcs/not_specified.py
strcs/py.typed
strcs/register.py
strcs/standard.py
strcs/version.py
strcs/disassemble/__init__.py
strcs/disassemble/_base.py
strcs/disassemble/_cache.py
strcs/disassemble/_comparer.py
strcs/disassemble/_creation.py
strcs/disassemble/_extract.py
strcs/disassemble/_fields.py
strcs/disassemble/_instance_check.py
strcs/disassemble/_score.py
strcs/disassemble/_type_tree.py
strcs-0.5.0.dist-info/METADATA
strcs-0.5.0.dist-info/WHEEL
strcs-0.5.0.dist-info/licenses/LICENSE
strcs-0.5.0.dist-info/RECORD
