Metadata-Version: 2.4
Name: strcs
Version: 0.5.0
Summary: Wrapper to make it more convenient to make structure hooks for cattrs
Project-URL: repository, https://github.com/delfick/strcs
Project-URL: changelog, https://strcs.readthedocs.io/en/latest/strcs/changelog.html
Project-URL: docs, https://strcs.readthedocs.io
Author-email: Stephen Moore <stephen@delfick.com>
License: MIT
License-File: LICENSE
Classifier: Intended Audience :: Developers
Classifier: License :: OSI Approved :: MIT License
Classifier: Operating System :: OS Independent
Classifier: Programming Language :: Python :: 3
Classifier: Programming Language :: Python :: 3 :: Only
Classifier: Programming Language :: Python :: 3.13
Classifier: Typing :: Typed
Requires-Python: >=3.13
Requires-Dist: attrs>=22.2.0
Requires-Dist: cattrs<=23.2.3,>=22.2.0
